{
  "symbol": "QBE.AX",
  "analysis_period_days": 14,
  "data_points": 76,
  "correlations": {
    "sentiment_vs_price": {
      "pearson": -0.1480020518634703,
      "pearson_p_value": 0.20198798685398767,
      "spearman": -0.2820456888471356,
      "spearman_p_value": 0.013571731646961726,
      "significance": "not_significant"
    },
    "sentiment_vs_volatility": {
      "pearson": -0.18311220282512813,
      "interpretation": "very_weak_negative"
    },
    "sentiment_vs_volume": {
      "pearson": -0.011865488112960149,
      "interpretation": "very_weak_negative"
    },
    "lagged_correlations": {
      "1_day": -0.2153315021975446,
      "2_day": -0.28612316572390306,
      "3_day": -0.3580638599626603
    },
    "data_quality": {
      "total_points": 76,
      "valid_points": 76,
      "data_completeness": 1.0
    }
  },
  "event_impact": {
    "event_type_impacts": {
      "rating_change": {
        "avg_price_change_event_days": 0.4777917556838755,
        "avg_price_change_non_event_days": 0.2477230159033416,
        "difference": 0.2300687397805339,
        "event_count": 41,
        "volatility_event_days": 0.7247326677975403,
        "volatility_non_event_days": 0.9107111423814168
      },
      "earnings_report": {
        "avg_price_change_event_days": 0.18528552319354857,
        "avg_price_change_non_event_days": 0.4215866528093179,
        "difference": -0.23630112961576932,
        "event_count": 16,
        "volatility_event_days": 0.5254484699264843,
        "volatility_non_event_days": 0.8797738602590558
      },
      "merger_acquisition": {
        "avg_price_change_event_days": 0.6914865572156428,
        "avg_price_change_non_event_days": -0.00260518017672861,
        "difference": 0.6940917373923714,
        "event_count": 41,
        "volatility_event_days": 0.5404341478513655,
        "volatility_non_event_days": 0.9333763721965854
      }
    },
    "summary": {
      "highest_impact_positive": [
        "merger_acquisition",
        0.6940917373923714
      ],
      "highest_impact_negative": [
        "earnings_report",
        -0.23630112961576932
      ],
      "most_frequent_event": [
        "rating_change",
        41
      ],
      "average_impact": 0.22928644918571198
    }
  },
  "predictive_metrics": {
    "prediction_accuracy": 0.42105263157894735,
    "confusion_matrix": {
      "positive_sentiment": {
        "up": 0,
        "down": 0,
        "flat": 0
      },
      "negative_sentiment": {
        "up": 0,
        "down": 0,
        "flat": 0
      },
      "neutral_sentiment": {
        "up": 28,
        "down": 16,
        "flat": 32
      }
    },
    "total_predictions": 76,
    "correct_predictions": 32,
    "sentiment_distribution": {
      "positive": 0,
      "negative": 0,
      "neutral": 76
    },
    "price_distribution": {
      "up": 28,
      "down": 16,
      "flat": 32
    }
  },
  "summary": "Sentiment-price correlation: -0.148 (not_significant). Weak correlation suggests other factors dominate price movements. ",
  "recommendations": [
    "No significant sentiment-price correlation. Focus on technical/fundamental analysis."
  ],
  "analysis_timestamp": "2025-07-18T07:54:25.138910",
  "analysis_version": "1.0"
}